x13binary/__init__.py
x13binary/__main__.py
x13binary-v1.1.61.dist-info/licenses/x13binary/LICENSE
x13binary-v1.1.61.data/scripts/x13as_html
x13binary-v1.1.61.dist-info/METADATA
x13binary-v1.1.61.dist-info/WHEEL
x13binary-v1.1.61.dist-info/RECORD
