Metadata-Version: 2.4
Name: x13binary
Version: v1.1.61
Summary: X13-ARIMA-SEATS installable binary through Python.
License-Expression: MIT
License-File: x13binary/LICENSE
Classifier: Development Status :: 4 - Beta
Classifier: Intended Audience :: Developers
Classifier: Programming Language :: Fortran
Classifier: Topic :: Scientific/Engineering :: Mathematics
Classifier: Topic :: Software Development :: Build Tools
Project-URL:
Project-URL: Source Code, https://github.com/bryceclaughton/x13binary-pypi
Project-URL:
Requires-Python: ~=3.5
